{
  "number": 24013,
  "projections": {
    "threethirtyeight": {
      "party": "lpc",
      "confidence": 1
    },
    "calculatedPolitics": {
      "party": "lpc",
      "confidence": 1
    }
  },
  "scores": [
    {
      "party": "lpc",
      "score": 1
    }
  ],
  "winner": {
    "party": "lpc",
    "score": 1
  },
  "name": "Thérèse-De Blainville",
  "position": {
    "y": -73.84150321773635,
    "x": 45.67708193506151
  },
  "bounds": [
    [
      45.62903206792293,
      -73.9256729806078
    ],
    [
      45.7247218140645,
      -73.7450763108662
    ]
  ]
}