{
  "number": 59013,
  "projections": {
    "threethirtyeight": {
      "party": "cpc",
      "confidence": 1
    },
    "calculatedPolitics": {
      "party": "cpc",
      "confidence": 1
    }
  },
  "scores": [
    {
      "party": "cpc",
      "score": 1
    }
  ],
  "winner": {
    "party": "cpc",
    "score": 1
  },
  "name": "Kamloops--Thompson--Cariboo",
  "position": {
    "y": -120.43267408106722,
    "x": 51.55914403865778
  },
  "bounds": [
    [
      50.357835249128804,
      -122.67742479062944
    ],
    [
      52.87786898599715,
      -118.78649116969417
    ]
  ]
}